{
  "clientName": "John Doe",
  "clientPhoneNumber": "9876543210",
  "clientEmail": "john.doe@example.com",
  "clientAadhaar": "123412341234",
  "item": {
    "name": "Silk Saree",
    "size": "L",
    "price": 2499,
    "quantity": 2
  },
  "deliveryDate": "2025-09-12",
  "returnDate": "2025-09-19",
  "notes": "Gift wrap and handle with care",
  "customerDetail": "66f2c0f2a9a3b0c6d4e12345",
  "deliveryAddress": [
    {
      "street": "12 MG Road",
      "city": "Bengaluru",
      "state": "Karnataka",
      "postalCode": "560001",
      "country": "India",
      "landmark": "Near Metro Station",
      "isPrimary": true
    }
  ]
}
